kpsv2_client/__init__.py
kpsv2_client/kps_helper.py
kpsv2_client/service.py
kpsv2_client-0.1.0.dist-info/LICENSE
kpsv2_client-0.1.0.dist-info/METADATA
kpsv2_client-0.1.0.dist-info/WHEEL
kpsv2_client-0.1.0.dist-info/RECORD
