Metadata-Version: 2.1
Name: kpsv2-client
Version: 0.1.0
Summary: A client package for kpsv2.nvi.gov.tr
License: MIT
Author: Ülkü Bayraktar
Author-email: ulkubayraktar@gmail.com
Requires-Python: >=3.9,<4.0
Classifier: License :: OSI Approved :: MIT License
Classifier: Programming Language :: Python :: 3
Classifier: Programming Language :: Python :: 3.9
Classifier: Programming Language :: Python :: 3.10
Classifier: Programming Language :: Python :: 3.11
Requires-Dist: requests (>=2.28.2,<3.0.0)
